entry.py
core/__init__.py
core/arguments.py
core/colors.py
core/dnsfunc.py
core/nmap.py
core/settings.py
core/subdomains.py
list/subdomains.txt
elixir_dns-1.1.0.dist-info/LICENSE
elixir_dns-1.1.0.dist-info/METADATA
elixir_dns-1.1.0.dist-info/WHEEL
elixir_dns-1.1.0.dist-info/entry_points.txt
elixir_dns-1.1.0.dist-info/top_level.txt
elixir_dns-1.1.0.dist-info/RECORD
