Metadata-Version: 2.1
Name: elixir-dns
Version: 1.1.0
Summary: Elixir is a fast multi-function DNS Enumeration, Subdomain Enumeration and Attack Surface Mapping tool.
Home-page: https://github.com/B0lg0r0v/Elixir
Author: B0lg0r0v
Author-email: contact@arthurminasyan.com
Maintainer: B0lg0r0v
License: MIT
Platform: Unix
Classifier: Development Status :: 5 - Production/Stable
Classifier: Intended Audience :: Developers
Classifier: License :: OSI Approved :: MIT License
Classifier: Programming Language :: Python :: 3.10
Classifier: Programming Language :: Python :: 3.11
Classifier: Programming Language :: Python :: 3.12
License-File: LICENSE
Requires-Dist: beautifulsoup4
Requires-Dist: dnspython
Requires-Dist: requests
Requires-Dist: setuptools
